Metadata-Version: 2.1
Name: turoboro
Version: 0.0.4
Summary: A python library for specifying recurring time rules and getting timestamps in return.
Home-page: https://github.com/pellepim/turoboro
Author: Jon Nylander
Author-email: pellepim@gmail.com
License: UNKNOWN
Platform: UNKNOWN
Classifier: Programming Language :: Python :: 3
Classifier: License :: OSI Approved :: MIT License
Classifier: Operating System :: OS Independent
